tstructs/__init__.py
tstructs/cell.py
tstructs/chunkedregion.py
tstructs/coord.py
tstructs/group.py
tstructs/properties.py
tstructs/region.py
tstructs-1.2.0.dist-info/LICENSE
tstructs-1.2.0.dist-info/METADATA
tstructs-1.2.0.dist-info/WHEEL
tstructs-1.2.0.dist-info/top_level.txt
tstructs-1.2.0.dist-info/RECORD
