Metadata-Version: 2.1
Name: tstructs
Version: 1.2.0
Summary: This package provides foundational data structures for representing and manipulating tile maps in 2D and 3D environments. Its primary purpose is to enable efficient spatial organization and management of map data for games, simulations, and applications that require robust handling of coordinates, regions, and chunked regions. By offering specialized classes for coordinates, regions, and chunked regions, the package simplifies the development of systems that need precise and scalable ma
Home-page: https://github.com/uaineteine/tstructs.pydat
Author: Daniel Stamer-Squair
Author-email: uaine.teine@hotmail.com
Classifier: Programming Language :: Python :: 3
Classifier: License :: OSI Approved :: GNU General Public License v3 (GPLv3)
Classifier: Operating System :: OS Independent
Requires-Python: >=3.8
License-File: LICENSE
